componentdependencies/__init__.py
componentdependencies/componentdependency.py
componentdependencies/interface.py
componentdependencies/test.py
TracComponentDependency-0.3.dist-info/METADATA
TracComponentDependency-0.3.dist-info/WHEEL
TracComponentDependency-0.3.dist-info/entry_points.txt
TracComponentDependency-0.3.dist-info/top_level.txt
TracComponentDependency-0.3.dist-info/RECORD
