Metadata-Version: 2.1
Name: TracComponentDependency
Version: 0.3
Summary: allows plugins to depend on other components being enabled
Home-page: https://trac-hacks.org/wiki/ComponentDependencyPlugin
Author: Jeff Hammel
Author-email: jhammel@openplans.org
License: BSD 3-Clause
Keywords: trac plugin
Platform: UNKNOWN
Classifier: Framework :: Trac
